pexel_downloader/__init__.py
pexel_downloader/downloader.py
pexel_downloader/pexel_downloader.py
pexel_downloader-0.4.0.dist-info/LICENSE
pexel_downloader-0.4.0.dist-info/METADATA
pexel_downloader-0.4.0.dist-info/WHEEL
pexel_downloader-0.4.0.dist-info/entry_points.txt
pexel_downloader-0.4.0.dist-info/top_level.txt
pexel_downloader-0.4.0.dist-info/RECORD
