Metadata-Version: 2.1
Name: pexel_downloader
Version: 0.4.0
Summary: A package for downloading images from Pexels.
Home-page: https://github.com/Gabriellgpc/pexel-downloader
Author: Luis Condados
Author-email: condadoslgpc@gmail.com
Classifier: Programming Language :: Python :: 3
Classifier: License :: OSI Approved :: MIT License
Classifier: Operating System :: OS Independent
Requires-Python: >=3.8
License-File: LICENSE
Requires-Dist: requests
Requires-Dist: joblib
Requires-Dist: click
Requires-Dist: tqdm
